{
  "name": "hedgehog-ide",
  "dependencies": {},
  "globalDependencies": {
    "core-js": "registry:dt/core-js#0.0.0+20160914114559",
    "hammerjs": "registry:dt/hammerjs#2.0.8+20160724063812",
    "hapi": "registry:dt/hapi#13.0.0+20160928135445",
    "jquery": "registry:dt/jquery#1.10.0+20160929162922",
    "node": "registry:dt/node#6.0.0+20161010101523",
    "nodegit": "github:FlorianKoerner/nodegit-typescript-definition/nodegit.d.ts"
  },
  "globalDevDependencies": {
    "mocha": "registry:dt/mocha#2.2.5+20160720003353",
    "rimraf": "registry:dt/rimraf#0.0.0+20160317120654"
  }
}
